uh_halp/__init__.py
uh_halp/__main__.py
uh_halp/config.py
uh_halp/default_config.json
uh_halp/keys.py
uh_halp/main.py
uh_halp/vars.py
uh_halp/backend/__init__.py
uh_halp/backend/openai.py
uh_halp/backend/util.py
uh_halp/backend/web_api.py
uh_halp-0.1.8.dist-info/entry_points.txt
uh_halp-0.1.8.dist-info/WHEEL
uh_halp-0.1.8.dist-info/METADATA
uh_halp-0.1.8.dist-info/RECORD
