Metadata-Version: 2.4
Name: uh_halp
Version: 0.1.8
Summary: Get command line help using AI
Author-email: Gareth Davidson <gaz@bitplane.net>
Requires-Python: >=3.8
Classifier: Programming Language :: Python :: 3
Classifier: License :: Public Domain
Classifier: Operating System :: OS Independent
Classifier: Environment :: Console
Requires-Dist: openai==0.28.*
Requires-Dist: requests>=2.31
Requires-Dist: flake8 ; extra == "dev"
Requires-Dist: pre-commit ; extra == "dev"
Requires-Dist: pytest ; extra == "dev"
Requires-Dist: pytest-cov ; extra == "dev"
Requires-Dist: coverage ; extra == "dev"
Requires-Dist: build ; extra == "dev"
Requires-Dist: twine ; extra == "dev"
Requires-Dist: pydoc-markdown ; extra == "dev"
Project-URL: Bug Tracker, https://github.com/bitplane/uh-halp/issues
Project-URL: Homepage, https://github.com/bitplane/uh-halp
Provides-Extra: dev
